Workbook
Name aporte: 'Simulador de investimento'!$K$16
Name patrimonio: 'Simulador de investimento'!$K$19
Name prazo_anos: 'Simulador de investimento'!$K$17
Name rendimento_carteira: 'Simulador de investimento'!$K$11
Name rendimento_mensal: 'Simulador de investimento'!$K$18
Name salario: 'Simulador de investimento'!$K$10
Name sugestao_invest: 'Simulador de investimento'!$K$12

Sheet Simulador de investimento
J9: CONFIGURAÇÕES
J10: Salário | K10: 2000
J11: Rendimento Carteira | K11: 0.006
J12: Sugestão de Investimento (30%) | K12: =K10*30% -> 600
J15: INVESTIMENTO MENSAL
J16: Quanto investir por mês? | K16: 601
J17: Por quantos anos? | K17: 9
J18: Taxa de rendimento mensal? | K18: 0.01079
J19: Patrimônio acumulado? | K19: =FV(rendimento_mensal,prazo_anos*12,aporte)*-1 -> 121814.92
J20: Dividendos mensais? | K20: =patrimonio*rendimento_carteira -> 730.88954
J23: CENÁRIOS
J24: PRAZO | K24: PATRIMÔNIO ACUMULADO | L24: DIVIDENDO
J25: 2 Anos | K25: =FV(rendimento_mensal,2*12,aporte)*-1 -> 16363.804 | L25: =K25*rendimento_carteira -> 98.182824
J26: 5 Anos | K26: =FV($K$18,5*12,$K$16)*-1 -> 50349.925 | L26: =K26*rendimento_carteira -> 302.09955
J27: 10 Anos | K27: =FV($K$18,10*12,$K$16)*-1 -> 146213.81 | L27: =K27*rendimento_carteira -> 877.28287
J28: 20 Anos | K28: =FV($K$18,20*12,$K$16)*-1 -> 676244.24 | L28: =K28*rendimento_carteira -> 4057.4654
J29: 30 Anos | K29: =FV($K$18,30*12,$K$16)*-1 -> 2597624 | L29: =K29*rendimento_carteira -> 15585.744
J32: PERFIL | K32: MODERADO
J33: Investimento mensal | K33: =aporte -> 601
J35: TIPO DE FII | K35: Percentual Sugerido | L35: Valores
J36: PAPEL | K36: =VLOOKUP($K$32&"-"&J36,'Tipo de Investimento'!A3:D21,4,FALSE) -> 0.22 | L36: =K36*$K$33 -> 132.22
J37: TIJOLO | K37: =VLOOKUP($K$32&"-"&J37,'Tipo de Investimento'!A4:D22,4,FALSE) -> 0.4 | L37: =K37*$K$33 -> 240.4
J38: HÍBRIDOS | K38: =VLOOKUP($K$32&"-"&J38,'Tipo de Investimento'!A5:D23,4,FALSE) -> 0.08 | L38: =K38*$K$33 -> 48.08
J39: FOFs | K39: =VLOOKUP($K$32&"-"&J39,'Tipo de Investimento'!A6:D24,4,FALSE) -> 0.1 | L39: =K39*$K$33 -> 60.1
J40: DESENVOLVIMENTO | K40: =VLOOKUP($K$32&"-"&J40,'Tipo de Investimento'!A7:D25,4,FALSE) -> 0.1 | L40: =K40*$K$33 -> 60.1
J41: HOTELARIAS | K41: =VLOOKUP($K$32&"-"&J41,'Tipo de Investimento'!A8:D26,4,FALSE) -> 0.1 | L41: =K41*$K$33 -> 60.1
J42: TOTAL | K42: =SUM(K36:K41) -> 1 | L42: =SUM(L36:L41) -> 601

Sheet Tipo de Investimento
A3: CHAVE | B3: PERFIL | C3: TIPO DE FII | D3: PERCENTUAL
A4: =$B$4&"-"&C4 -> CONSERVADOR-PAPEL | B4: CONSERVADOR | C4: PAPEL | D4: 0.3
A5: =$B$4&"-"&C5 -> CONSERVADOR-TIJOLO | B5: CONSERVADOR | C5: TIJOLO | D5: 0.5
A6: =$B$4&"-"&C6 -> CONSERVADOR-HÍBRIDOS | B6: CONSERVADOR | C6: HÍBRIDOS | D6: 0.1
A7: =$B$4&"-"&C7 -> CONSERVADOR-FOFs | B7: CONSERVADOR | C7: FOFs | D7: 0.1
A8: =$B$4&"-"&C8 -> CONSERVADOR-DESENVOLVIMENTO | B8: CONSERVADOR | C8: DESENVOLVIMENTO | D8: 0
A9: =$B$4&"-"&C9 -> CONSERVADOR-HOTELARIAS | B9: CONSERVADOR | C9: HOTELARIAS | D9: 0
A10: =$B$10&"-"&C10 -> MODERADO-PAPEL | B10: MODERADO | C10: PAPEL | D10: 0.22
A11: =$B$10&"-"&C11 -> MODERADO-TIJOLO | B11: MODERADO | C11: TIJOLO | D11: 0.4
A12: =$B$10&"-"&C12 -> MODERADO-HÍBRIDOS | B12: MODERADO | C12: HÍBRIDOS | D12: 0.08
A13: =$B$10&"-"&C13 -> MODERADO-FOFs | B13: MODERADO | C13: FOFs | D13: 0.1
A14: =$B$10&"-"&C14 -> MODERADO-DESENVOLVIMENTO | B14: MODERADO | C14: DESENVOLVIMENTO | D14: 0.1
A15: =$B$10&"-"&C15 -> MODERADO-HOTELARIAS | B15: MODERADO | C15: HOTELARIAS | D15: 0.1
A16: =$B$16&"-"&C16 -> AGRESSIVO-PAPEL | B16: AGRESSIVO | C16: PAPEL | D16: 0.5
A17: =$B$16&"-"&C17 -> AGRESSIVO-TIJOLO | B17: AGRESSIVO | C17: TIJOLO | D17: 0.1
A18: =$B$16&"-"&C18 -> AGRESSIVO-HÍBRIDOS | B18: AGRESSIVO | C18: HÍBRIDOS | D18: 0.05
A19: =$B$16&"-"&C19 -> AGRESSIVO-FOFs | B19: AGRESSIVO | C19: FOFs | D19: 0.05
A20: =$B$16&"-"&C20 -> AGRESSIVO-DESENVOLVIMENTO | B20: AGRESSIVO | C20: DESENVOLVIMENTO | D20: 0.2
A21: =$B$16&"-"&C21 -> AGRESSIVO-HOTELARIAS | B21: AGRESSIVO | C21: HOTELARIAS | D21: 0.1
